rhubarb/__init__.py
rhubarb/analyze.py
rhubarb/classification/__init__.py
rhubarb/classification/classification.py
rhubarb/classification/sampling.py
rhubarb/classify.py
rhubarb/config/__init__.py
rhubarb/config/config.py
rhubarb/file_converter/__init__.py
rhubarb/file_converter/file_converter.py
rhubarb/file_converter/image_validator.py
rhubarb/file_converter/large_document_processor.py
rhubarb/invocations/__init__.py
rhubarb/invocations/invocations.py
rhubarb/models.py
rhubarb/schema_factory/__init__.py
rhubarb/schema_factory/default_models.py
rhubarb/schema_factory/entities.py
rhubarb/schema_factory/fewshot/sample_schema.json
rhubarb/schema_factory/schema_factory.py
rhubarb/schema_factory/single_doc_schemas/chat_schema.json
rhubarb/schema_factory/single_doc_schemas/classification_schema.json
rhubarb/schema_factory/single_doc_schemas/default_schema.json
rhubarb/schema_factory/single_doc_schemas/figure_schema.json
rhubarb/schema_factory/single_doc_schemas/multiclass_schema.json
rhubarb/schema_factory/single_doc_schemas/ner_schema.json
rhubarb/schema_factory/single_doc_schemas/sample_schema.json
rhubarb/services/__init__.py
rhubarb/services/services.py
rhubarb/services/tools_syndicate.py
rhubarb/system_prompts/__init__.py
rhubarb/system_prompts/sysprompts/prompts.json
rhubarb/system_prompts/system_prompts.py
rhubarb/system_prompts/system_prompts_v2.py
rhubarb/system_prompts/video_prompts.py
rhubarb/user_prompts/__init__.py
rhubarb/user_prompts/user_prompt.py
rhubarb/utility/__init__.py
rhubarb/utility/s3utility.py
rhubarb/video_processor/__init__.py
rhubarb/video_processor/video_analyzer.py
pyrhubarb-0.0.7.dist-info/LICENSE
pyrhubarb-0.0.7.dist-info/METADATA
pyrhubarb-0.0.7.dist-info/NOTICE
pyrhubarb-0.0.7.dist-info/WHEEL
pyrhubarb-0.0.7.dist-info/RECORD
