Metadata-Version: 2.3
Name: pyrhubarb
Version: 0.0.7
Summary: A Python framework for multi-modal document understanding with generative AI
License: Apache 2.0
Author: Rhubarb Developers
Author-email: rhubarb-developers@amazon.com
Requires-Python: >=3.11
Classifier: License :: OSI Approved :: Apache Software License
Classifier: License :: Other/Proprietary License
Classifier: Operating System :: OS Independent
Classifier: Programming Language :: Python :: 3
Classifier: Programming Language :: Python :: 3.11
Classifier: Programming Language :: Python :: 3.12
Classifier: Programming Language :: Python :: 3.13
Requires-Dist: fastparquet (>=2024.5.0,<2025.0.0)
Requires-Dist: jsonschema (>=4.21.1,<5.0.0)
Requires-Dist: pdfplumber (>=0.11.0,<0.12.0)
Requires-Dist: pillow (>=10.3.0,<11.0.0)
Requires-Dist: pydantic (>=2.6.4,<3.0.0)
Project-URL: Documentation, https://github.com/awslabs/rhubarb
Project-URL: Homepage, https://github.com/awslabs/rhubarb
Project-URL: Issues, https://github.com/awslabs/rhubarb/issues
Project-URL: Repository, https://github.com/awslabs/rhubarb
